kafkaconnect/__init__.py
kafkaconnect/cli.py
kafkaconnect/config.py
kafkaconnect/connect.py
kafkaconnect/topic_names_set.py
kafkaconnect/influxdb_sink/__init__.py
kafkaconnect/influxdb_sink/cli.py
kafkaconnect/influxdb_sink/config.py
kafkaconnect/jdbc_sink/__init__.py
kafkaconnect/jdbc_sink/cli.py
kafkaconnect/mirrormaker2/__init__.py
kafkaconnect/mirrormaker2/cli.py
kafkaconnect/s3_sink/__init__.py
kafkaconnect/s3_sink/cli.py
kafkaconnect-1.3.1.dist-info/LICENSE
kafkaconnect-1.3.1.dist-info/METADATA
kafkaconnect-1.3.1.dist-info/WHEEL
kafkaconnect-1.3.1.dist-info/entry_points.txt
kafkaconnect-1.3.1.dist-info/top_level.txt
kafkaconnect-1.3.1.dist-info/RECORD
