Metadata-Version: 2.1
Name: kafkaconnect
Version: 1.3.1
Summary: Python client for managing Kafka connectors.
Home-page: https://github.com/lsst-sqre/kafka-connect-manager
Author: Association of Universities for Research in Astronomy, Inc. (AURA)
Author-email: sqre-admin@lists.lsst.org
Project-URL: Change log, https://github.com/lsst-sqre/kafka-connect-manager/blob/master/CHANGELOG.rst
Project-URL: Source code, https://github.com/lsst-sqre/kafka-connect-manager
Project-URL: Issue tracker, https://github.com/lsst-sqre/kafka-connect-manager/issues
Keywords: lsst
Classifier: Development Status :: 4 - Beta
Classifier: License :: OSI Approved :: MIT License
Classifier: Programming Language :: Python
Classifier: Programming Language :: Python :: 3
Classifier: Programming Language :: Python :: 3.11
Classifier: Natural Language :: English
Classifier: Operating System :: POSIX
Requires-Python: >=3.11
License-File: LICENSE
